config_parser_module/__init__.py
config_parser_module/config_reader.py
tests/__init__.py
tests/test_config_parser_module.py
Configify_Wizard-0.1.2.dist-info/METADATA
Configify_Wizard-0.1.2.dist-info/WHEEL
Configify_Wizard-0.1.2.dist-info/top_level.txt
Configify_Wizard-0.1.2.dist-info/RECORD
